verifyshopify/__init__.py
verifyshopify/verify.py
verifyshopify-0.1.7.dist-info/METADATA
verifyshopify-0.1.7.dist-info/WHEEL
verifyshopify-0.1.7.dist-info/RECORD
