Metadata-Version: 2.1
Name: verifyshopify
Version: 0.1.7
Summary: This module provides a utility function to verify the authenticity of data received from Shopify webhooks. It uses HMAC (Hash-based Message Authentication Code) with SHA-256 hashing to ensure that the data has not been tampered with in transit.
Home-page: https://github.com/zinyosrim/shopify-webhook-verification
License: MIT
Author: Zin Yosrim
Author-email: zinyosrim@gmail.com
Requires-Python: >=3.9,<4.0
Classifier: Intended Audience :: Developers
Classifier: License :: OSI Approved :: MIT License
Classifier: Operating System :: OS Independent
Classifier: Programming Language :: Python :: 3
Classifier: Programming Language :: Python :: 3.9
Classifier: Programming Language :: Python :: 3.10
Classifier: Programming Language :: Python :: 3.11
Classifier: Topic :: Security
Classifier: Topic :: Software Development :: Libraries :: Python Modules
Requires-Dist: requests (>=2.31.0,<3.0.0)
Project-URL: Repository, https://github.com/zinyosrim/shopify-webhook-verification
